{"segments":[{"inverted":true,"paths":[{"x":2.166,"y":2.895},{"x":2.167,"y":2.825},{"x":2.111,"y":2.767},{"x":2.059,"y":2.753}],"constraints":{"velocity":71,"accel":141}},{"inverted":false,"paths":[{"x":2.059,"y":2.753},{"x":2.19,"y":2.72},{"x":2.237,"y":2.596},{"x":2.198,"y":2.459}],"constraints":{"velocity":45,"accel":141}},{"inverted":false,"paths":[{"x":2.304,"y":2.307},{"x":2.246,"y":2.147},{"x":1.939,"y":2.271},{"x":1.763,"y":2.376}],"constraints":{"velocity":30,"accel":141}},{"inverted":false,"paths":[{"x":1.76,"y":2.386},{"x":1.739,"y":2.581},{"x":1.741,"y":2.781},{"x":1.734,"y":3.097}],"constraints":{"velocity":25,"accel":141}}],"commands":[{"t":1.86,"name":"leftWingIn"}]}